crawl_redfin/__init__.py
crawl_redfin/helpers.py
crawl_redfin/htmlparser.py
crawl_redfin/urlencoder.py
crawl_redfin/zzz_manual_install.py
crawl_redfin/__pycache__/__init__.cpython-34.pyc
crawl_redfin/const/__init__.py
crawl_redfin/const/house_type.py
crawl_redfin/pkg/__init__.py
crawl_redfin/pkg/constant2/__init__.py
crawl_redfin/pkg/constant2/_constant2.py
crawl_redfin/pkg/constant2/zzz_manual_install.py
crawl_redfin/pkg/constant2/pkg/__init__.py
crawl_redfin/pkg/constant2/pkg/pylru.py
crawl_redfin/pkg/constant2/pkg/pytest.py
crawl_redfin/pkg/constant2/pkg/sixmini.py
crawl_redfin/pkg/constant2/pkg/inspect_mate/__init__.py
crawl_redfin/pkg/constant2/pkg/inspect_mate/getter.py
crawl_redfin/pkg/constant2/pkg/inspect_mate/tester.py
crawl_redfin/pkg/constant2/pkg/inspect_mate/zzz_manual_install.py
crawl_redfin/pkg/constant2/pkg/inspect_mate/tests/__init__.py
crawl_redfin/pkg/constant2/pkg/superjson/__init__.py
crawl_redfin/pkg/constant2/pkg/superjson/_superjson.py
crawl_redfin/pkg/constant2/pkg/superjson/comments.py
crawl_redfin/pkg/constant2/pkg/superjson/compresslib.py
crawl_redfin/pkg/constant2/pkg/superjson/util.py
crawl_redfin/pkg/constant2/pkg/superjson/warning.py
crawl_redfin/pkg/constant2/pkg/superjson/zzz_manual_install.py
crawl_redfin/pkg/constant2/pkg/superjson/pkg/__init__.py
crawl_redfin/pkg/constant2/pkg/superjson/pkg/six.py
crawl_redfin/pkg/constant2/pkg/superjson/pkg/dateutil/__init__.py
crawl_redfin/pkg/constant2/pkg/superjson/pkg/dateutil/_common.py
crawl_redfin/pkg/constant2/pkg/superjson/pkg/dateutil/_version.py
crawl_redfin/pkg/constant2/pkg/superjson/pkg/dateutil/easter.py
crawl_redfin/pkg/constant2/pkg/superjson/pkg/dateutil/parser.py
crawl_redfin/pkg/constant2/pkg/superjson/pkg/dateutil/relativedelta.py
crawl_redfin/pkg/constant2/pkg/superjson/pkg/dateutil/rrule.py
crawl_redfin/pkg/constant2/pkg/superjson/pkg/dateutil/tzwin.py
crawl_redfin/pkg/constant2/pkg/superjson/pkg/dateutil/pkg/__init__.py
crawl_redfin-0.0.3.dist-info/DESCRIPTION.rst
crawl_redfin-0.0.3.dist-info/METADATA
crawl_redfin-0.0.3.dist-info/RECORD
crawl_redfin-0.0.3.dist-info/WHEEL
crawl_redfin-0.0.3.dist-info/metadata.json
crawl_redfin-0.0.3.dist-info/top_level.txt
